twosheds/__init__.py
twosheds/cli.py
twosheds/completer.py
twosheds/grammar.py
twosheds/language.py
twosheds/semantics.py
twosheds/shell.py
twosheds/transform.py
twosheds-0.1.2.dist-info/DESCRIPTION.rst
twosheds-0.1.2.dist-info/METADATA
twosheds-0.1.2.dist-info/pydist.json
twosheds-0.1.2.dist-info/RECORD
twosheds-0.1.2.dist-info/top_level.txt
twosheds-0.1.2.dist-info/WHEEL
