Metadata-Version: 2.0
Name: twosheds
Version: 0.1.2
Summary: extensible Python shell
Home-page: https://github.com/Ceasar/twosheds
Author: Ceasar Bautista
Author-email: cbautista2010@gmail.com
License: MIT
Keywords: twosheds,shell
Platform: UNKNOWN
Classifier: Intended Audience :: Developers
Classifier: License :: OSI Approved :: MIT License
Classifier: Operating System :: OS Independent
Classifier: Programming Language :: Python
Classifier: Programming Language :: Python :: 2.5
Classifier: Programming Language :: Python :: 2.6
Classifier: Programming Language :: Python :: 2.7
Classifier: Topic :: Software Development :: Libraries :: Python Modules
Classifier: Development Status :: 4 - Beta
Classifier: Intended Audience :: Developers
